miska/__init__.py
miska/compare.py
miska/dataclasses.py
miska/dicts.py
miska/enums.py
miska/group.py
miska/mixins.py
miska/registries.py
miska/http/__init__.py
miska/http/rs.py
miska/mm/__init__.py
miska/mm/fields.py
miska/mm/validators.py
miska/types/__init__.py
miska/types/network/__init__.py
miska/types/network/bgp.py
miska-0.1.5.dist-info/licenses/LICENSE
miska-0.1.5.dist-info/METADATA
miska-0.1.5.dist-info/WHEEL
miska-0.1.5.dist-info/top_level.txt
miska-0.1.5.dist-info/RECORD
