Metadata-Version: 2.4
Name: miska
Version: 0.1.5
Summary: Miska-llaneous code, tools and stuff
Author-email: Dima Burmistrov <pyctrl.dev@gmail.com>
License: Copyright (c) 2023-2024 Dmitry Burmistrov
Project-URL: Homepage, https://gitlab.com/pyctrl/miska
Project-URL: Bug Tracker, https://gitlab.com/pyctrl/miska/-/issues
Keywords: misc,miska
Classifier: Programming Language :: Python :: 3
Classifier: License :: OSI Approved :: MIT License
Classifier: Operating System :: OS Independent
Classifier: Development Status :: 4 - Beta
Classifier: Intended Audience :: Developers
Classifier: Topic :: Software Development :: Libraries :: Python Modules
Requires-Python: >=3.11
License-File: LICENSE
Provides-Extra: http
Requires-Dist: requests; extra == "http"
Provides-Extra: mm
Requires-Dist: marshmallow; extra == "mm"
Provides-Extra: ddd
Requires-Dist: izulu; extra == "ddd"
Provides-Extra: all
Requires-Dist: miska[ddd,http,mm]; extra == "all"
Dynamic: license-file
